delfinance/__init__.py
delfinance_python_sdk-0.0.4.dist-info/METADATA
delfinance_python_sdk-0.0.4.dist-info/WHEEL
delfinance_python_sdk-0.0.4.dist-info/top_level.txt
delfinance_python_sdk-0.0.4.dist-info/RECORD
