Metadata-Version: 2.4
Name: delfinance-python-sdk
Version: 0.0.4
Summary: SDK oficial da Delfinance para Python
Home-page: https://github.com/delfinance/python-sdk
Author: Delfinance Team
Author-email: dev@delfinance.com
Project-URL: Bug Tracker, https://github.com/delfinance/python-sdk/issues
Classifier: Programming Language :: Python :: 3
Classifier: Programming Language :: Python :: 3.7
Classifier: License :: OSI Approved :: MIT License
Classifier: Operating System :: OS Independent
Requires-Python: >=3.7
Requires-Dist: requests>=2.31.0
Requires-Dist: python-dotenv>=0.21.1
Dynamic: author
Dynamic: author-email
Dynamic: classifier
Dynamic: description
Dynamic: description-content-type
Dynamic: home-page
Dynamic: project-url
Dynamic: requires-dist
Dynamic: requires-python
Dynamic: summary
